{
  "version": 0.6,
  "generator": "Overpass API 0.7.62.1 084b4234",
  "osm3s": {
    "timestamp_osm_base": "2024-04-29T10:59:05Z",
    "copyright": "The data included in this document is from www.openstreetmap.org. The data is made available under ODbL."
  },
  "elements": [
    {
      "type": "way",
      "id": 880759175,
      "bounds": {
        "minlat": 41.0018723,
        "minlon": 28.9714160,
        "maxlat": 41.0021465,
        "maxlon": 28.9751811
      },
      "nodes": [
        3044788469,
        3178899571,
        4548145321,
        3044788466,
        4548145312,
        6779632168,
        6779632169,
        3131825239,
        9383461391,
        3131825234,
        3044788477,
        6779632173,
        3131823028
      ],
      "geometry": [
        {
          "lat": 41.0018723,
          "lon": 28.9714160
        },
        {
          "lat": 41.0019169,
          "lon": 28.9716618
        },
        {
          "lat": 41.0019505,
          "lon": 28.9719940
        },
        {
          "lat": 41.0019689,
          "lon": 28.9722253
        },
        {
          "lat": 41.0020243,
          "lon": 28.9729004
        },
        {
          "lat": 41.0020508,
          "lon": 28.9734461
        },
        {
          "lat": 41.0020537,
          "lon": 28.9735064
        },
        {
          "lat": 41.0020681,
          "lon": 28.9738027
        },
        {
          "lat": 41.0020861,
          "lon": 28.9740435
        },
        {
          "lat": 41.0021047,
          "lon": 28.9742911
        },
        {
          "lat": 41.0021355,
          "lon": 28.9746811
        },
        {
          "lat": 41.0021447,
          "lon": 28.9751007
        },
        {
          "lat": 41.0021465,
          "lon": 28.9751811
        }
      ],
      "tags": {
        "cycleway:right": "shared_lane",
        "highway": "primary",
        "horse": "no",
        "lanes": "2",
        "maxspeed": "90",
        "name": "Kennedy Caddesi",
        "name:ru": "улица Кеннеди",
        "oneway": "yes",
        "surface": "asphalt"
      }
    },
    {
      "type": "way",
      "id": 1017327567,
      "bounds": {
        "minlat": 41.0020457,
        "minlon": 28.9715481,
        "maxlat": 41.0021914,
        "maxlon": 28.9748446
      },
      "nodes": [
        1055371979,
        3131825236,
        248137337,
        6779632172,
        1055371984,
        1055371988,
        3131823023,
        1055371990
      ],
      "geometry": [
        {
          "lat": 41.0021914,
          "lon": 28.9748446
        },
        {
          "lat": 41.0021438,
          "lon": 28.9738582
        },
        {
          "lat": 41.0021340,
          "lon": 28.9736774
        },
        {
          "lat": 41.0021317,
          "lon": 28.9736350
        },
        {
          "lat": 41.0021120,
          "lon": 28.9732674
        },
        {
          "lat": 41.0020457,
          "lon": 28.9719264
        },
        {
          "lat": 41.0020577,
          "lon": 28.9716481
        },
        {
          "lat": 41.0020614,
          "lon": 28.9715481
        }
      ],
      "tags": {
        "cycleway:right": "shared_lane",
        "highway": "primary",
        "horse": "no",
        "lanes": "2",
        "maxspeed": "90",
        "name": "Kennedy Caddesi",
        "name:ru": "улица Кеннеди",
        "oneway": "yes",
        "surface": "asphalt"
      }
    },
    {
      "type": "way",
      "id": 1115520572,
      "bounds": {
        "minlat": 41.0018168,
        "minlon": 28.9703463,
        "maxlat": 41.0018723,
        "maxlon": 28.9714160
      },
      "nodes": [
        4187848293,
        10202092339,
        4187848292,
        5414833288,
        10202092337,
        3044788469
      ],
      "geometry": [
        {
          "lat": 41.0018676,
          "lon": 28.9703463
        },
        {
          "lat": 41.0018359,
          "lon": 28.9704927
        },
        {
          "lat": 41.0018193,
          "lon": 28.9706763
        },
        {
          "lat": 41.0018168,
          "lon": 28.9709530
        },
        {
          "lat": 41.0018342,
          "lon": 28.9712242
        },
        {
          "lat": 41.0018723,
          "lon": 28.9714160
        }
      ],
      "tags": {
        "cycleway:right": "shared_lane",
        "highway": "primary",
        "horse": "no",
        "lanes": "2",
        "lit": "yes",
        "maxspeed": "90",
        "name": "Kennedy Caddesi",
        "name:ru": "улица Кеннеди",
        "oneway": "yes",
        "surface": "asphalt"
      }
    },
    {
      "type": "way",
      "id": 1150257895,
      "bounds": {
        "minlat": 41.0020614,
        "minlon": 28.9703452,
        "maxlat": 41.0023457,
        "maxlon": 28.9715481
      },
      "nodes": [
        1055371990,
        1055371992,
        2370366647,
        1055371994,
        3131825235
      ],
      "geometry": [
        {
          "lat": 41.0020614,
          "lon": 28.9715481
        },
        {
          "lat": 41.0021266,
          "lon": 28.9711646
        },
        {
          "lat": 41.0022284,
          "lon": 28.9707409
        },
        {
          "lat": 41.0022797,
          "lon": 28.9705689
        },
        {
          "lat": 41.0023457,
          "lon": 28.9703452
        }
      ],
      "tags": {
        "cycleway:right": "shared_lane",
        "highway": "primary",
        "horse": "no",
        "lanes": "2",
        "maxspeed": "90",
        "name": "Kennedy Caddesi",
        "name:ru": "улица Кеннеди",
        "oneway": "yes"
      }
    }
  ]
}